tqchain/_version.py
tqchain/keys.py
tqchain/mkchain.py
tqchain/parameters.yaml
mkchain-6.25.0.dist-info/METADATA
mkchain-6.25.0.dist-info/WHEEL
mkchain-6.25.0.dist-info/entry_points.txt
mkchain-6.25.0.dist-info/top_level.txt
mkchain-6.25.0.dist-info/RECORD
