Metadata-Version: 2.1
Name: mkchain
Version: 6.25.0
Summary: A utility to generate k8s configs for a Tezos blockchain
Home-page: https://github.com/oxheadalpha/tezos-k8s
Author: TQ Tezos
License: UNKNOWN
Platform: UNKNOWN
Classifier: Programming Language :: Python :: 3
Classifier: License :: OSI Approved :: MIT License
Classifier: Operating System :: OS Independent
Requires-Python: >=3.7
Requires-Dist: pyyaml
Provides-Extra: dev
Requires-Dist: pytest ; extra == 'dev'
Requires-Dist: autoflake ; extra == 'dev'
Requires-Dist: isort ; extra == 'dev'
Requires-Dist: black ; extra == 'dev'
